b3denv/__init__.py
b3denv/__main__.py
b3denv-0.0.21.dist-info/METADATA
b3denv-0.0.21.dist-info/WHEEL
b3denv-0.0.21.dist-info/entry_points.txt
b3denv-0.0.21.dist-info/licenses/LICENSE
b3denv-0.0.21.dist-info/RECORD
