Metadata-Version: 2.4
Name: b3denv
Version: 0.0.21
Summary: Help with blender python
Project-URL: Homepage, https://github.com/coldtype/b3denv
Author-email: Rob Stenson / Coldtype <rob@goodhertz.com>
License-File: LICENSE
Classifier: Operating System :: OS Independent
Classifier: Programming Language :: Python :: 3
Classifier: Programming Language :: Python :: 3.10
Requires-Python: >=3.10
